efile/__init__.py
efile/__main__.py
efile/efile.py
efile-1.0.1.dist-info/METADATA
efile-1.0.1.dist-info/RECORD
efile-1.0.1.dist-info/WHEEL
efile-1.0.1.dist-info/entry_points.txt
efile-1.0.1.dist-info/top_level.txt
