Metadata-Version: 2.1
Name: efile
Version: 1.0.1
Summary: efile
Home-page: https://github.com/orooro/efile
Author: orooro
Author-email: orooro@gmail.com
License: MIT
Platform: UNKNOWN
Classifier: Development Status :: 4 - Beta
Classifier: Topic :: Utilities
Classifier: License :: OSI Approved :: MIT License
Classifier: Programming Language :: Python :: 3 :: Only
